<annotation>
  <folder></folder>
  <filename>frame0608.jpg</filename>
  <source>
    <database>Unknown</database>
    <annotation>Unknown</annotation>
    <image>Unknown</image>
  </source>
  <size>
    <width>1920</width>
    <height>1080</height>
    <depth></depth>
  </size>
  <segmented>0</segmented>
  <object>
    <name>motion</name>
    <occluded>0</occluded>
    <bndbox>
      <xmin>112.85</xmin>
      <ymin>211.27</ymin>
      <xmax>128.85</xmax>
      <ymax>222.27</ymax>
    </bndbox>
  </object>
  <object>
    <name>motion</name>
    <occluded>0</occluded>
    <bndbox>
      <xmin>528.0</xmin>
      <ymin>292.0</ymin>
      <xmax>587.0</xmax>
      <ymax>324.0</ymax>
    </bndbox>
  </object>
  <object>
    <name>motion</name>
    <occluded>0</occluded>
    <bndbox>
      <xmin>403.0</xmin>
      <ymin>290.0</ymin>
      <xmax>420.0</xmax>
      <ymax>305.0</ymax>
    </bndbox>
  </object>
  <object>
    <name>motion</name>
    <occluded>0</occluded>
    <bndbox>
      <xmin>93.0</xmin>
      <ymin>186.0</ymin>
      <xmax>109.0</xmax>
      <ymax>197.0</ymax>
    </bndbox>
  </object>
  <object>
    <name>motion</name>
    <occluded>0</occluded>
    <bndbox>
      <xmin>809.0</xmin>
      <ymin>408.0</ymin>
      <xmax>833.0</xmax>
      <ymax>418.0</ymax>
    </bndbox>
  </object>
  <object>
    <name>motion</name>
    <occluded>0</occluded>
    <bndbox>
      <xmin>489.0</xmin>
      <ymin>294.0</ymin>
      <xmax>510.0</xmax>
      <ymax>310.0</ymax>
    </bndbox>
  </object>
  <object>
    <name>motion</name>
    <occluded>0</occluded>
    <bndbox>
      <xmin>251.0</xmin>
      <ymin>224.0</ymin>
      <xmax>302.0</xmax>
      <ymax>247.0</ymax>
    </bndbox>
  </object>
  <object>
    <name>motion</name>
    <occluded>0</occluded>
    <bndbox>
      <xmin>1790.68</xmin>
      <ymin>642.41</ymin>
      <xmax>1819.04</xmax>
      <ymax>659.71</ymax>
    </bndbox>
  </object>
</annotation>
