<annotation>
  <folder></folder>
  <filename>frame0325.jpg</filename>
  <source>
    <database>Unknown</database>
    <annotation>Unknown</annotation>
    <image>Unknown</image>
  </source>
  <size>
    <width>1920</width>
    <height>1080</height>
    <depth></depth>
  </size>
  <segmented>0</segmented>
  <object>
    <name>motion</name>
    <occluded>0</occluded>
    <bndbox>
      <xmin>453.0</xmin>
      <ymin>580.0</ymin>
      <xmax>516.0</xmax>
      <ymax>617.0</ymax>
    </bndbox>
  </object>
</annotation>
