<annotation>
  <folder></folder>
  <filename>frame0361.jpg</filename>
  <source>
    <database>Unknown</database>
    <annotation>Unknown</annotation>
    <image>Unknown</image>
  </source>
  <size>
    <width>1920</width>
    <height>1080</height>
    <depth></depth>
  </size>
  <segmented>0</segmented>
  <object>
    <name>motion</name>
    <occluded>0</occluded>
    <bndbox>
      <xmin>1445.49</xmin>
      <ymin>653.51</ymin>
      <xmax>1474.25</xmax>
      <ymax>674.78</ymax>
    </bndbox>
  </object>
  <object>
    <name>motion</name>
    <occluded>0</occluded>
    <bndbox>
      <xmin>1253.0</xmin>
      <ymin>599.0</ymin>
      <xmax>1267.0</xmax>
      <ymax>613.0</ymax>
    </bndbox>
  </object>
  <object>
    <name>motion</name>
    <occluded>0</occluded>
    <bndbox>
      <xmin>1165.26</xmin>
      <ymin>578.43</ymin>
      <xmax>1178.92</xmax>
      <ymax>589.75</ymax>
    </bndbox>
  </object>
  <object>
    <name>motion</name>
    <occluded>0</occluded>
    <bndbox>
      <xmin>1064.27</xmin>
      <ymin>546.55</ymin>
      <xmax>1077.94</xmax>
      <ymax>557.87</ymax>
    </bndbox>
  </object>
  <object>
    <name>motion</name>
    <occluded>0</occluded>
    <bndbox>
      <xmin>1131.99</xmin>
      <ymin>568.33</ymin>
      <xmax>1145.66</xmax>
      <ymax>579.65</ymax>
    </bndbox>
  </object>
  <object>
    <name>motion</name>
    <occluded>0</occluded>
    <bndbox>
      <xmin>1372.0</xmin>
      <ymin>629.0</ymin>
      <xmax>1397.0</xmax>
      <ymax>644.0</ymax>
    </bndbox>
  </object>
</annotation>
