<annotation>
  <folder></folder>
  <filename>frame0113.jpg</filename>
  <source>
    <database>Unknown</database>
    <annotation>Unknown</annotation>
    <image>Unknown</image>
  </source>
  <size>
    <width>1920</width>
    <height>1080</height>
    <depth></depth>
  </size>
  <segmented>0</segmented>
  <object>
    <name>motion</name>
    <occluded>0</occluded>
    <bndbox>
      <xmin>1258.0</xmin>
      <ymin>649.0</ymin>
      <xmax>1297.0</xmax>
      <ymax>680.0</ymax>
    </bndbox>
  </object>
  <object>
    <name>motion</name>
    <occluded>0</occluded>
    <bndbox>
      <xmin>1866.08</xmin>
      <ymin>862.42</ymin>
      <xmax>1920.0</xmax>
      <ymax>892.38</ymax>
    </bndbox>
  </object>
  <object>
    <name>motion</name>
    <occluded>0</occluded>
    <bndbox>
      <xmin>826.27</xmin>
      <ymin>397.55</ymin>
      <xmax>836.27</xmax>
      <ymax>406.55</ymax>
    </bndbox>
  </object>
  <object>
    <name>motion</name>
    <occluded>0</occluded>
    <bndbox>
      <xmin>1073.98</xmin>
      <ymin>537.21</ymin>
      <xmax>1097.1</xmax>
      <ymax>557.67</ymax>
    </bndbox>
  </object>
  <object>
    <name>motion</name>
    <occluded>0</occluded>
    <bndbox>
      <xmin>921.46</xmin>
      <ymin>484.29</ymin>
      <xmax>936.97</xmax>
      <ymax>497.36</ymax>
    </bndbox>
  </object>
  <object>
    <name>motion</name>
    <occluded>0</occluded>
    <bndbox>
      <xmin>1217.74</xmin>
      <ymin>605.12</ymin>
      <xmax>1244.02</xmax>
      <ymax>628.02</ymax>
    </bndbox>
  </object>
</annotation>
