<annotation>
  <folder></folder>
  <filename>frame0123.jpg</filename>
  <source>
    <database>Unknown</database>
    <annotation>Unknown</annotation>
    <image>Unknown</image>
  </source>
  <size>
    <width>1920</width>
    <height>1080</height>
    <depth></depth>
  </size>
  <segmented>0</segmented>
  <object>
    <name>motion</name>
    <occluded>0</occluded>
    <bndbox>
      <xmin>923.16</xmin>
      <ymin>478.67</ymin>
      <xmax>934.98</xmax>
      <ymax>489.51</ymax>
    </bndbox>
  </object>
  <object>
    <name>motion</name>
    <occluded>0</occluded>
    <bndbox>
      <xmin>1728.0</xmin>
      <ymin>804.0</ymin>
      <xmax>1796.0</xmax>
      <ymax>847.0</ymax>
    </bndbox>
  </object>
  <object>
    <name>motion</name>
    <occluded>0</occluded>
    <bndbox>
      <xmin>1121.0</xmin>
      <ymin>554.0</ymin>
      <xmax>1146.0</xmax>
      <ymax>583.0</ymax>
    </bndbox>
  </object>
  <object>
    <name>motion</name>
    <occluded>0</occluded>
    <bndbox>
      <xmin>1218.0</xmin>
      <ymin>631.0</ymin>
      <xmax>1251.0</xmax>
      <ymax>656.0</ymax>
    </bndbox>
  </object>
  <object>
    <name>motion</name>
    <occluded>0</occluded>
    <bndbox>
      <xmin>1299.13</xmin>
      <ymin>631.12</ymin>
      <xmax>1333.13</xmax>
      <ymax>659.12</ymax>
    </bndbox>
  </object>
  <object>
    <name>motion</name>
    <occluded>0</occluded>
    <bndbox>
      <xmin>840.87</xmin>
      <ymin>406.95</ymin>
      <xmax>850.87</xmax>
      <ymax>415.95</ymax>
    </bndbox>
  </object>
  <object>
    <name>motion</name>
    <occluded>0</occluded>
    <bndbox>
      <xmin>814.51</xmin>
      <ymin>385.38</ymin>
      <xmax>824.3</xmax>
      <ymax>392.2</ymax>
    </bndbox>
  </object>
  <object>
    <name>motion</name>
    <occluded>0</occluded>
    <bndbox>
      <xmin>797.73</xmin>
      <ymin>380.35</ymin>
      <xmax>806.57</xmax>
      <ymax>386.91</ymax>
    </bndbox>
  </object>
</annotation>
