<annotation>
  <folder></folder>
  <filename>frame0052.jpg</filename>
  <source>
    <database>Unknown</database>
    <annotation>Unknown</annotation>
    <image>Unknown</image>
  </source>
  <size>
    <width>1920</width>
    <height>1080</height>
    <depth></depth>
  </size>
  <segmented>0</segmented>
  <object>
    <name>motion</name>
    <occluded>0</occluded>
    <bndbox>
      <xmin>932.0</xmin>
      <ymin>477.0</ymin>
      <xmax>944.0</xmax>
      <ymax>492.0</ymax>
    </bndbox>
  </object>
  <object>
    <name>motion</name>
    <occluded>0</occluded>
    <bndbox>
      <xmin>886.0</xmin>
      <ymin>435.0</ymin>
      <xmax>899.0</xmax>
      <ymax>450.0</ymax>
    </bndbox>
  </object>
  <object>
    <name>motion</name>
    <occluded>0</occluded>
    <bndbox>
      <xmin>756.0</xmin>
      <ymin>342.0</ymin>
      <xmax>766.0</xmax>
      <ymax>351.0</ymax>
    </bndbox>
  </object>
  <object>
    <name>motion</name>
    <occluded>0</occluded>
    <bndbox>
      <xmin>1849.14</xmin>
      <ymin>901.5</ymin>
      <xmax>1920.0</xmax>
      <ymax>947.1</ymax>
    </bndbox>
  </object>
  <object>
    <name>motion</name>
    <occluded>0</occluded>
    <bndbox>
      <xmin>942.0</xmin>
      <ymin>534.0</ymin>
      <xmax>972.0</xmax>
      <ymax>554.0</ymax>
    </bndbox>
  </object>
</annotation>
